<?xml version="1.0"?>
<?xml-stylesheet type="text/xsl" href="OC_1_2_Properties_WFIP_HWS3.xsl"?>
<Data>
  <Image TextDescription="">
    <Attachment Name="PreviewMarker" Application="LAS AF" IsPreviewImage="0" />
    <ImageDescription>
      <Name>OC_1_2</Name>
      <Size>18.87 MB</Size>
      <UniqueID>aa836720-e582-11ef-8baf-3417eb9dd5ab</UniqueID>
      <Channels>
        <ChannelDescription DataType="0" ChannelTag="3" Resolution="8" NameOfMeasuredQuantity="" Min="0.000000e+000" Max="2.550000e+002" Unit="" LUTName="Blue" IsLUTInverted="0" BytesInc="0" BitInc="0" OpticalResolutionXY="76.791 µm" OpticalResolutionZ="28813.671 µm">
        </ChannelDescription>
        <ChannelDescription DataType="0" ChannelTag="2" Resolution="8" NameOfMeasuredQuantity="" Min="0.000000e+000" Max="2.550000e+002" Unit="" LUTName="Green" IsLUTInverted="0" BytesInc="1" BitInc="0" OpticalResolutionXY="76.791 µm" OpticalResolutionZ="28813.671 µm">
        </ChannelDescription>
        <ChannelDescription DataType="0" ChannelTag="1" Resolution="8" NameOfMeasuredQuantity="" Min="0.000000e+000" Max="2.550000e+002" Unit="" LUTName="Red" IsLUTInverted="0" BytesInc="2" BitInc="0" OpticalResolutionXY="76.791 µm" OpticalResolutionZ="28813.671 µm">
        </ChannelDescription>
      </Channels>
      <Dimensions>
        <DimensionDescription DimID="X" NumberOfElements="3072" Origin="0" Length="14.64" Unit="mm" BitInc="0" BytesInc="3" UnitOrigin="mm" EndPosition="14.64" UnitEndPosition="mm" LogicalUnit="pixels" Voxel="0.005">
        </DimensionDescription>
        <DimensionDescription DimID="Y" NumberOfElements="2048" Origin="0" Length="9.76" Unit="mm" BitInc="0" BytesInc="9216" UnitOrigin="mm" EndPosition="9.76" UnitEndPosition="mm" LogicalUnit="pixels" Voxel="0.005">
        </DimensionDescription>
      </Dimensions>
      <FileLocation>C:\Users\AMIC\Desktop\Crouch\020725\Ally_3xTg.lif</FileLocation>
      <StartTime>2/7/2025 1:38:05.329 PM</StartTime>
      <EndTime>2/7/2025 1:38:05.329 PM</EndTime>
      <FrameCount>3 (3 channels, 1 frames)</FrameCount>
      <NumberOfChannels>3</NumberOfChannels>
      <FluoDescription>
        <FluoDescriptionRecord Identifier="Channel 0" Name="New 1" Contrast="FREE" Excitation="" Emission="0" Cube="Empty" Intensity="0" />
      </FluoDescription>
    </ImageDescription>
    <TimeStampList NumberOfTimeStamps="1" FirstTimeStampDate="2/7/2025" FirstTimeStampTime="1:38:05 PM" FirstTimeStampMiliSeconds="329">1db798f6cfbd810 <TimeStamp RelativeTime="0.000" Date="2/7/2025" Time="1:38:05 PM" MiliSeconds="329" /></TimeStampList>
    <Attachment Name="ChannelAttachment" Application="LAS AF" />
    <Attachment Name="ViewerScaling" Application="LAS AF">
      <ChannelScalingInfo BackgroundLutName="" WhiteValue="1" BlackValue="0" GammaValue="1" Automatic="0" />
      <ChannelScalingInfo BackgroundLutName="" WhiteValue="1" BlackValue="0" GammaValue="1" Automatic="0" />
      <ChannelScalingInfo BackgroundLutName="" WhiteValue="1" BlackValue="0" GammaValue="1" Automatic="0" />
    </Attachment>
    <Attachment Name="ImageXMLDocument" Application="LAS AF">
      <RootNode />
    </Attachment>
    <Attachment Name="HardwareSetting" Application="LAS AF" Software="LAS X 3.7.5.24914" HardwareServerVersion="Build 24914" SystemType="11" SystemTypeName="AF 6000" DataSourceType="1" DataSourceTypeName="Camera">
      <ATLCameraSettingDefinition VersionNumber="5" SpimMirrorMode="1" MirrorX="0" MirrorY="0" TheoCamSensorPixelSizeX="0.0000023984375" TheoCamSensorPixelSizeY="0.0000023984375" Gamma="1" Brightness="201" WhiteValue="255" BlackValue="0" GainValue="7.078125" GainStringValue="0" IsGainUsedAsStringList="0" CanDoEMGain="0" CanDoColorSat="1" EMGainValue="1" OffsetValue="0" ColorSat="33" AutoBright="0" AutoExposure="0" AutoContrastGamma="219" BinningText="6.3MP, 3072x2048, 3:2" LiveBinningText="" ScanMode="xy" ZUseMode="0" ZUseModeName="nothing" ZPosition="0 mm" IsSuperZ="0" Begin="0" End="0" Sections="1" CycleCount="1" CycleTime="0" UseMaxIterationsForT="0" CompleteTime="0.021583999954164" IsTimeMinimizeEnabled="0" LastTCalcMode="3" ValidBeginStack="0" ValidEndStack="0" StackCalculationMode="2" StackCalculationModeName="System optimized step size" ZStackDirectionMode="1" ZStackDirectionModeName="Unidirectional" IsLinkedShadingEnabled="0" Magnification="0.503" CanDoTotalVideoMag="1" TotalVideoMag="0.503" AutofocusChannel="1" IsAutofocusOnStart="0" AutofocusRedoEveryNTimePoints="0" ObjectiveName="     1x/0.00  " ObjectiveNumber="10450028" ObjectivePos="0" MicroscopeModel="M125" IsInverseMicroscopeModel="0" ShutterMode="1" ShutterModeSoftware="0" CanDoIndustryShuttering="0" Immersion="" NumericalAperture="0.004369" RefractionIndex="1" MountingMediumRefractionIndex="1" CoverslipThickness="0.00017" TubeOpticName="" TubeOpticPos="-1" TubeOpticPortMagPos="0" CanDoChangeSpeedAndPort="0" CanDoColorCapture="1" CanDoMicroScanning="0" CanDoDualLightMode="0" CanDoLiveBinning="0" CanDoControlCooler="0" CanDoControlTemperature="0" CanDoFanControl="0" CanDoHotSpotCorrection="0" CanDoBrightnessCorrection="1" IsBrightnessCorrectionActive="1" SCMOSReadoutMode="0" CanDoEnhancedAcquisitionMode="1" HDR_DigitalFusion_Mode="3" CurrentLightSheetFilterPosition="0" BinningValuePrecise="1" BinningXValuePrecise="1" BinningYValuePrecise="1" ZStackUseMode="1" NbStepsForEDOF="10" MaxNbStepsForStartUp="20" CalcEDoFfromZStack="0" CalcEDoFfromZStackForStartUp="0" EnhancedAcquisitionHDREnable="0" EnhancedAcquisitionHDRAutomatic="1" EnhancedAcquisitionHDRContrast="0" EnhancedAcquisitionHDRBrightness="50" IsSequencerAdvancedUseEnabled="0" PortCameraPercentage="100" UserManagementUserName="UserManagementFeatureInactive">
        <Autofocus-config VersionNumber="1" Precision="2" FocusRange="0" ZUseMode="0" ZUseModeName="nothing" AFAnalyseType="4" AFAnalyseTypeName="FirstChannelOnly" WorkflowTimelapse="2" WorkflowTimelapseName="AllTime" WorkflowTimelapseIterator="1" WorkflowXY="2" WorkflowXYName="AllPos" WorkflowXYIterator="1" UseFixSliceNumber="0" AFSubsystem="0" AFSubsystemName="BaseAF" AFCOffset="-2" AFCAutonomousOffset="-2" AutoFocusMode="2" AutoFocusModeName="FirstChannelOnly" AutofocusChannel="1" AutofocusChannelName="2000" OptimalStepSize="2.09552974315235E-02" PositionDimension="122" />
        <AdditionalZPositionList />
        <Quantity Value="2.09552974315235E-02" Unit="" />
        <ZStackUseModeInfo ZStackUseMode="1" StackCalcMode="0" ValidBegin="0" ValidEnd="0" BeginValue="0" EndValue="0" NbSections="1">
          <Quantity Value="0" Unit="" />
        </ZStackUseModeInfo>
        <WideFieldChannelConfigurator MicroscopeFamilyType="3" CameraName="K3C-700008224968" CameraType="420" CameraNamePure="K3C" CameraColorCaptureMode="0" MaxChannelCount="1" CurrentChannelIndex="0" eZUseMode="0" eStackFlowMode="2" IsUseSameExposureTime="0" SameExposureTime="0.008367" IsUseSameZoom="1" SameZoom="0.8" WFCCCameranRoiLeftHightX="0" WFCCCameranRoiLeftHightY="0" WFCCCameranRoiRightButtomX="3072" WFCCCameranRoiRightButtomY="2048" WFCCCameranRoiIsUsed="0" FastFilterWheel1="-1" FastFilterWheel2="-1" FastFilterWheel3="-1" FastFilterWheel4="-1" ExtensionMode="0" IsStereoTLFinetuningBase="0" TypeOfStereoTLBase="-1" CanDoFREEIllumination="1" CanDoStereoIris="1" CanDoOnlineShadingCorrection="1" OnlineShadingCorrectionDefinitionState="0" OnlineShadingCorrectionActivationState="0" OnlineShadingCorrectionNotificationsEnabled="0" OnlineShadingCorrection="0" IsSimpleOperation="0" CanDoStageRotation="0" StageRotationAngle="0" CanDoColumnTilt="0" ColumnTiltAngle="0">
          <WideFieldChannelInfo Channel="2000" Active="1" FluoCubePos="2" Intensity="0" IntensityMode="700" ExposureTime="1.584 ms" ContrastingMethodName="FREE" ContrastingMethod="401" Gain="7.078125" GainString="0" StringGainName="" EMGain="1" SpinDiskFilterSetPosition="0" SpinDiskUse="0" FluoChromeName="" UserDefName="New 1" FluoCubeName="Empty" EmissionWavelength="550" DyeName="" LUT="P.Color 5" BackgroundLUT="" BlackValue="0" WhiteValue="1" GammaValue="1" SpinDiskFilterSetName="" ColorGainValueR="12.9779227120536" ColorGainValueG="1" ColorGainValueB="13.2783203125" WhiteBalanceBaseValueR="12.9779227120536" WhiteBalanceBaseValueG="1" WhiteBalanceBaseValueB="13.2783203125" ColorWheelValueR="255" ColorWheelValueG="255" ColorWheelValueB="255" FFW_Excitation1Position="0" FFW_Excitation2Position="0" FFW_Emission1Position="0" FFW_Emission2Position="0" FFW_Excitation1PositionDev="0" FFW_Excitation2PositionDev="0" FFW_Emission1PositionDev="0" FFW_Emission2PositionDev="0" FFW_Excitation1FilterName="" FFW_Excitation2FilterName="" FFW_Emission1FilterName="" FFW_Emission2FilterName="" FieldDiaphragmValue="-1" ApertureDiaphragmValue="-1" OnlineShadingCorrectionReferenceID="-1" OnlineShadingCorrectionReferenceParentID="-1" FilteredOnlineShadingCorrectionReferenceID="-1" OnlineShadingCorrectionDefinitionState="-1" OnlineShadingCorrectionReferenceImageName="" StereoTLBase_Aperture="0" StereoTLBase_Tilt="0" StereoTLBase_Position="0" MicZoom="0.8" StereoTLZoomApertureControlMode="0" StereoTLContrastMode="-1" IrisValue="20" CCICCurrentPos="-1" />
          <AdvancedCameraFeatures Advanced_Camera_Features_Activated="1">
            <CameraFeature Name="Averaging" Camera_Feature_160_Value="2.000000" Camera_Feature_160_Enabled="1" Camera_Feature_160_UIEnabled="1" />
            <CameraFeature Name="Sharpening" Camera_Feature_400_Value="0.000000" Camera_Feature_400_Enabled="0" Camera_Feature_400_UIEnabled="1" />
            <CameraFeature Name="Color temperature" Camera_Feature_100020_Value="4500" Camera_Feature_100020_Enabled="1" Camera_Feature_100020_UIEnabled="1" />
          </AdvancedCameraFeatures>
        </WideFieldChannelConfigurator>
        <CameraFormat xDim="3072" yDim="2048" Resolution="8" IsGray="0" Binning="1" LiveBinning="2" ColorCaptureMode="0" SimAcqMode="1" />
      </ATLCameraSettingDefinition>
    </Attachment>
  </Image>
</Data>